agora_wot/__init__.py
agora_wot/metadata.json
agora_wot/ns.py
agora_wot/utils.py
agora_wot/blocks/__init__.py
agora_wot/blocks/eco.py
agora_wot/blocks/endpoint.py
agora_wot/blocks/evaluate.py
agora_wot/blocks/operators.py
agora_wot/blocks/rdfsource.py
agora_wot/blocks/resource.py
agora_wot/blocks/td.py
agora_wot/blocks/ted.py
agora_wot/gateway/__init__.py
agora_wot/gateway/lifting.py
agora_wot/gateway/path.py
agora_wot/gateway/proxy.py
agora_wot/gateway/publish.py
agora_wot-0.2.20.dist-info/LICENSE
agora_wot-0.2.20.dist-info/METADATA
agora_wot-0.2.20.dist-info/WHEEL
agora_wot-0.2.20.dist-info/top_level.txt
agora_wot-0.2.20.dist-info/RECORD
