Metadata-Version: 2.1
Name: agora-wot
Version: 0.2.20
Summary: A Python-based framework for describing, discovering and accessing a Web of Things
Home-page: https://github.com/fserena/agora-wot
Author: Fernando Serena
Author-email: kudhmud@gmail.com
License: Apache 2
Download-URL: https://github.com/fserena/agora-wot/tarball/0.2.20
Keywords: interoperability,wot,agora,linked-data
Platform: UNKNOWN
Requires-Dist: agora-py
Requires-Dist: requests
Requires-Dist: SPARQLWrapper
Requires-Dist: rdflib (==4.2.1)
Requires-Dist: python-dateutil
Requires-Dist: pyld
Requires-Dist: rdflib-jsonld
Requires-Dist: networkx
Requires-Dist: shortuuid
Requires-Dist: jsonpath-rw
Requires-Dist: jsonpath-ng
Requires-Dist: gunicorn
